[
  { "排名": 1, "组织": "521", "名字": "三大大", "分数": 100019583 },
  { "排名": 3, "组织": "521", "名字": "丶初九", "分数": 83641703 },
  { "排名": 4, "组织": "KKK", "名字": "云海冬天", "分数": 39744403 },
  { "排名": 5, "组织": "521", "名字": "赣南脐橙太好吃了!", "分数": 37647546 },
  { "排名": 6, "组织": "KKK", "名字": "云海 冬天", "分数": 36268847 },
  { "排名": 7, "组织": "521", "名字": "暴暴小布丶", "分数": 34718621 },
  { "排名": 8, "组织": "521", "名字": "小黑鸡（时长2点5）", "分数": 34198949 },
  { "排名": 9, "组织": "b03", "名字": "BuBu丶（隐藏款）", "分数": 34189579 },
  { "排名": 10, "组织": "521", "名字": "千叶紫萧", "分数": 34138486 },
  { "排名": 11, "组织": "KKK", "名字": "喜羊羊", "分数": 34062082 },
  { "排名": 12, "组织": "001", "名字": "魔术师", "分数": 32897984 },
  {
    "排名": 13,
    "组织": "001",
    "名字": "日落黄昏（愚者控号）",
    "分数": 29420784
  },
  { "排名": 14, "组织": "001", "名字": "尢北风丶乔伊勿进", "分数": 29360536 },
  { "排名": 16, "组织": "QQQ", "名字": "皮皮鸡", "分数": 28800786 },
  { "排名": 17, "组织": "QQQ", "名字": "老黑不太黑", "分数": 28329279 },
  {
    "排名": 18,
    "组织": "521",
    "名字": "晴山栖谷（贝贝控号版）",
    "分数": 28058913
  },
  { "排名": 19, "组织": "QQQ", "名字": "无 言", "分数": 27960926 },
  { "排名": 20, "组织": "521", "名字": "木子矢口因心", "分数": 27774391 },
  { "排名": 21, "组织": "KKK", "名字": "多喝热水（飞鱼）", "分数": 27398858 },
  { "排名": 22, "组织": "521", "名字": "【悟空】", "分数": 26957918 },
  {
    "排名": 24,
    "组织": "521",
    "名字": "立志要当超级车头的秋波",
    "分数": 26370321
  },
  { "排名": 25, "组织": "QQQ", "名字": "Ayan", "分数": 25843326 },
  { "排名": 26, "组织": "KKK", "名字": "雾念枝枝", "分数": 25839372 },
  {
    "排名": 27,
    "组织": "QQQ",
    "名字": "茜茜公主Ceci·休养中",
    "分数": 25528002
  },
  { "排名": 28, "组织": "KKK", "名字": "小豆豆", "分数": 25214231 },
  { "排名": 29, "组织": "521", "名字": "蒲～（退游～）", "分数": 25212969 },
  { "排名": 30, "组织": "521", "名字": "gzy1231", "分数": 24215881 },
  { "排名": 31, "组织": "996", "名字": "是莫莫呀", "分数": 24104636 },
  {
    "排名": 32,
    "组织": "521",
    "名字": "人到中年，躺平只想拿低保",
    "分数": 22974223
  },
  { "排名": 33, "组织": "b01", "名字": "泡泡大王丶", "分数": 22921870 },
  { "排名": 34, "组织": "001", "名字": "太阳丶", "分数": 22732173 },
  { "排名": 35, "组织": "521", "名字": "Jr唐冬", "分数": 22665476 },
  { "排名": 36, "组织": "001", "名字": "倒吊人丶乔伊勿进", "分数": 22493868 },
  { "排名": 37, "组织": "QQQ", "名字": "沉默是金", "分数": 22402084 },
  { "排名": 38, "组织": "KKK", "名字": "种田~~流云", "分数": 22312151 },
  { "排名": 39, "组织": "QQQ", "名字": "遇见沉默", "分数": 21959002 },
  { "排名": 40, "组织": "521", "名字": "意想不到的结局", "分数": 21833052 },
  { "排名": 41, "组织": "KKK", "名字": "晓雪漫空山", "分数": 21780839 },
  { "排名": 42, "组织": "521", "名字": "航海家", "分数": 21773659 },
  { "排名": 43, "组织": "KKK", "名字": "呜呼哀哉", "分数": 21671024 },
  { "排名": 44, "组织": "521", "名字": "丶银河", "分数": 21304112 },
  { "排名": 45, "组织": "KKK", "名字": "流言蜚语（飞鱼）", "分数": 20990020 },
  { "排名": 46, "组织": "996", "名字": "多米是只猫", "分数": 20956359 },
  { "排名": 47, "组织": "521", "名字": "记住久一八、", "分数": 20940370 },
  { "排名": 48, "组织": "521", "名字": "吨吨吨吨鸽儿", "分数": 20246443 },
  { "排名": 50, "组织": "QQQ", "名字": "平安喜乐", "分数": 19735729 },
  { "排名": 52, "组织": "521", "名字": "别来影响我", "分数": 19313141 },
  {
    "排名": 54,
    "组织": "996",
    "名字": "煎饼果子加十八个鸡蛋",
    "分数": 18932888
  },
  { "排名": 55, "组织": "521", "名字": "晚星漫漫", "分数": 17693210 },
  { "排名": 56, "组织": "KKK", "名字": "追风逐日", "分数": 17561717 },
  { "排名": 57, "组织": "996", "名字": "山林溪", "分数": 17508179 },
  { "排名": 58, "组织": "KKK", "名字": "你瞅啥（冬天控号）", "分数": 17447166 },
  { "排名": 59, "组织": "521", "名字": "吃猫D鱼（养老）", "分数": 17194871 },
  { "排名": 60, "组织": "521", "名字": "汉堡III", "分数": 17049021 },
  { "排名": 61, "组织": "521", "名字": "想冬眠（摆烂ing）", "分数": 16735664 },
  { "排名": 62, "组织": "996", "名字": "海绵宝宝", "分数": 16537190 },
  { "排名": 63, "组织": "QQQ", "名字": "MIOMIO（皮皮猪代）", "分数": 16489862 },
  { "排名": 64, "组织": "KKK", "名字": "抱着鱼的风", "分数": 16447640 },
  { "排名": 65, "组织": "KKK", "名字": "7788", "分数": 16422549 },
  { "排名": 66, "组织": "KKK", "名字": "云海、冬天", "分数": 16110415 },
  { "排名": 67, "组织": "521", "名字": "抽根宽窄老壳不打铁", "分数": 15909542 },
  { "排名": 70, "组织": "996", "名字": "大雪无痕", "分数": 15639518 },
  { "排名": 71, "组织": "KKK", "名字": "麒麒小贝", "分数": 15585094 },
  { "排名": 73, "组织": "No1", "名字": "亚奇洛贝", "分数": 15375988 },
  { "排名": 74, "组织": "521", "名字": "狼图腾", "分数": 15356279 },
  { "排名": 76, "组织": "521", "名字": "咕咕鸡杀手", "分数": 15217245 },
  { "排名": 77, "组织": "521", "名字": "SANY", "分数": 15203237 },
  { "排名": 78, "组织": "QQQ", "名字": "Peter", "分数": 15127014 },
  { "排名": 79, "组织": "KKK", "名字": "小火车", "分数": 14979072 },
  { "排名": 81, "组织": "QQQ", "名字": "Yanli", "分数": 14927311 },
  { "排名": 83, "组织": "521", "名字": "一帘幽梦醉千年", "分数": 14900652 },
  { "排名": 84, "组织": "521", "名字": "北国 | 春城", "分数": 14836853 },
  { "排名": 85, "组织": "521", "名字": "五彩斑斓的面包", "分数": 14831970 },
  { "排名": 86, "组织": "KKK", "名字": "小雪爱初见", "分数": 14752716 },
  { "排名": 87, "组织": "QQQ", "名字": "燃 尽", "分数": 14745830 },
  { "排名": 88, "组织": "521", "名字": "麻子丶（零氪版）", "分数": 14699942 },
  { "排名": 89, "组织": "521", "名字": "为我低一次", "分数": 14670355 },
  { "排名": 90, "组织": "KKK", "名字": "Rainy night", "分数": 14651711 },
  { "排名": 91, "组织": "KKK", "名字": "九霄国际", "分数": 14459674 },
  { "排名": 92, "组织": "521", "名字": "蓝莓芝士", "分数": 14252919 },
  { "排名": 93, "组织": "996", "名字": "力争上游的学长", "分数": 14190888 },
  {
    "排名": 94,
    "组织": "521",
    "名字": "小二终于要熬成掌柜了",
    "分数": 14129164
  },
  { "排名": 95, "组织": "521", "名字": "西装98", "分数": 14125915 },
  { "排名": 96, "组织": "521", "名字": "董太师", "分数": 14025142 },
  { "排名": 97, "组织": "QQQ", "名字": "泡泡丶（退退退）", "分数": 14013266 },
  {
    "排名": 98,
    "组织": "QQQ",
    "名字": "MIOMI小（皮皮猪代）",
    "分数": 14006758
  },
  { "排名": 99, "组织": "521", "名字": "嘎嘎部落", "分数": 13973902 },
  { "排名": 100, "组织": "KKK", "名字": "那年东", "分数": 13852606 },
  {
    "排名": 101,
    "组织": "QQQ",
    "名字": "茜茜公主Ceci·休眠中",
    "分数": 13709750
  },
  { "排名": 102, "组织": "521", "名字": "想想别睡了", "分数": 13708276 },
  {
    "排名": 104,
    "组织": "521",
    "名字": "苹果看看五代英雄就淡游",
    "分数": 13560795
  },
  { "排名": 105, "组织": "QQQ", "名字": "波士顿矩阵", "分数": 13485951 },
  { "排名": 106, "组织": "521", "名字": "汽水加香草", "分数": 13476453 },
  { "排名": 107, "组织": "521", "名字": "斑秃猫", "分数": 13403769 },
  { "排名": 108, "组织": "QQQ", "名字": "菜鸡弱化版", "分数": 13325861 },
  { "排名": 109, "组织": "QQQ", "名字": "小懒熊", "分数": 13137811 },
  { "排名": 110, "组织": "QQQ", "名字": "皮皮噜（稀碎版）", "分数": 12842126 },
  {
    "排名": 112,
    "组织": "QQQ",
    "名字": "圣丶凯龙（皮皮猪）",
    "分数": 12318261
  },
  { "排名": 113, "组织": "521", "名字": "「贰广」", "分数": 12239184 },
  { "排名": 114, "组织": "KKK", "名字": "雪花开在冬天里", "分数": 12189272 },
  {
    "排名": 115,
    "组织": "QQQ",
    "名字": "尼罗河公主Q·休养中",
    "分数": 12169843
  },
  { "排名": 117, "组织": "521", "名字": "星辰大海", "分数": 11792413 },
  { "排名": 118, "组织": "KKK", "名字": "Master", "分数": 11656014 },
  { "排名": 119, "组织": "QQQ", "名字": "圣懒熊", "分数": 11301098 },
  { "排名": 120, "组织": "521", "名字": "草莓布丁", "分数": 11128132 },
  { "排名": 121, "组织": "521", "名字": "大大混子丶", "分数": 11125021 },
  { "排名": 122, "组织": "KKK", "名字": "林克爱冒险", "分数": 10947821 },
  {
    "排名": 123,
    "组织": "QQQ",
    "名字": "落落混日子（皮皮猪代）",
    "分数": 10844793
  },
  {
    "排名": 124,
    "组织": "AVN",
    "名字": "拾荒的老马（零氪度日）",
    "分数": 10804676
  },
  { "排名": 125, "组织": "KKK", "名字": "坚果是只短腿猫", "分数": 10629843 },
  { "排名": 126, "组织": "521", "名字": "da头豆腐", "分数": 10459987 },
  { "排名": 128, "组织": "KKK", "名字": "荒天帝", "分数": 10385967 },
  { "排名": 130, "组织": "KKK", "名字": "请茶馆", "分数": 10215259 },
  { "排名": 134, "组织": "KKK", "名字": "买冰茶还要分期的俺", "分数": 9996531 },
  { "排名": 135, "组织": "996", "名字": "会飞的鱼", "分数": 9990117 },
  { "排名": 138, "组织": "KKK", "名字": "这个冬天不太冷", "分数": 9901684 },
  { "排名": 139, "组织": "996", "名字": "吉祥止止", "分数": 9851872 },
  { "排名": 140, "组织": "521", "名字": "罗城主", "分数": 9798227 },
  { "排名": 142, "组织": "KKK", "名字": "多多酱", "分数": 9624128 },
  { "排名": 144, "组织": "996", "名字": "小茉椰椰", "分数": 9594761 },
  { "排名": 145, "组织": "QQQ", "名字": "塞伯坦星", "分数": 9486169 },
  { "排名": 148, "组织": "QQQ", "名字": "小皮皮猪", "分数": 9227578 },
  { "排名": 151, "组织": "521", "名字": "鸭梨山大大", "分数": 9088701 },
  { "排名": 155, "组织": "521", "名字": "夜鱼鱼", "分数": 8815019 },
  { "排名": 157, "组织": "521", "名字": "天 意", "分数": 8517867 },
  { "排名": 158, "组织": "521", "名字": "FiveFiveOpen", "分数": 8516015 },
  { "排名": 159, "组织": "000", "名字": "暖阳/老男孩", "分数": 8510627 },
  { "排名": 160, "组织": "KKK", "名字": "小&小", "分数": 8477163 },
  { "排名": 162, "组织": "QQQ", "名字": "绿豆糕点", "分数": 8345571 },
  { "排名": 165, "组织": "521", "名字": "多多多", "分数": 8259466 },
  { "排名": 169, "组织": "521", "名字": "君莫笑89", "分数": 8053988 },
  { "排名": 170, "组织": "521", "名字": "歪比巴卜", "分数": 7906480 },
  { "排名": 174, "组织": "521", "名字": "杨你一辈子", "分数": 7556781 },
  { "排名": 175, "组织": "QQQ", "名字": "小无言", "分数": 7543034 },
  { "排名": 176, "组织": "521", "名字": "幕天飞雪", "分数": 7512479 },
  { "排名": 178, "组织": "521", "名字": "大锤，2808颜值担当", "分数": 7361790 },
  { "排名": 179, "组织": "hgy", "名字": "掌柜，乔伊单防", "分数": 7301021 },
  { "排名": 182, "组织": "KKK", "名字": "如影随形", "分数": 7004570 },
  { "排名": 185, "组织": "QQQ", "名字": "时光可曾待你安好", "分数": 6907976 },
  { "排名": 186, "组织": "QQQ", "名字": "大懒熊", "分数": 6906364 },
  { "排名": 187, "组织": "KKK", "名字": "翠花花", "分数": 6879858 },
  { "排名": 188, "组织": "521", "名字": "小贝丶（发呆中）", "分数": 6876200 },
  { "排名": 189, "组织": "521", "名字": "吾既大灾变", "分数": 6861517 },
  { "排名": 192, "组织": "KKK", "名字": "鲜于十八", "分数": 6802083 },
  { "排名": 193, "组织": "QQQ", "名字": "无 聊", "分数": 6748356 },
  { "排名": 196, "组织": "123", "名字": "可可、", "分数": 6694243 },
  { "排名": 197, "组织": "521", "名字": "往事如风丶", "分数": 6673418 },
  { "排名": 198, "组织": "KKK", "名字": "艾宾浩斯", "分数": 6661654 },
  { "排名": 273, "组织": "521", "名字": "愚者丶", "分数": 5037143 }
]
